django_telegram_framework-5.0.1.dist-info/licenses/LICENSE
telegram_framework/__init__.py
telegram_framework/admin.py
telegram_framework/apps.py
telegram_framework/chats.py
telegram_framework/handlers.py
telegram_framework/models.py
telegram_framework/package.py
telegram_framework/user.py
telegram_framework/commands/__init__.py
telegram_framework/commands/actions.py
telegram_framework/commands/description.py
telegram_framework/commands/links.py
telegram_framework/dummy/__init__.py
telegram_framework/dummy/actions.py
telegram_framework/dummy/bots.py
telegram_framework/keyboards/__init__.py
telegram_framework/keyboards/layouts.py
telegram_framework/keyboards/force/__init__.py
telegram_framework/keyboards/force/keyboards.py
telegram_framework/keyboards/inline/__init__.py
telegram_framework/keyboards/inline/buttons.py
telegram_framework/keyboards/inline/keyboards.py
telegram_framework/keyboards/reply/__init__.py
telegram_framework/keyboards/reply/buttons.py
telegram_framework/keyboards/reply/keyboards.py
telegram_framework/links/__init__.py
telegram_framework/links/call_params.py
telegram_framework/links/command_params.py
telegram_framework/links/params.py
telegram_framework/management/__init__.py
telegram_framework/management/commands/__init__.py
telegram_framework/management/commands/run_bot.py
telegram_framework/messages/__init__.py
telegram_framework/messages/errors.py
telegram_framework/messages/call/__init__.py
telegram_framework/messages/call/call.py
telegram_framework/messages/call/call_base.py
telegram_framework/messages/core/__init__.py
telegram_framework/messages/core/chat_message.py
telegram_framework/messages/core/core_message_base.py
telegram_framework/messages/core/core_message_default.py
telegram_framework/messages/core/keyboard_message.py
telegram_framework/messages/media/__init__.py
telegram_framework/messages/media/image.py
telegram_framework/messages/media/image_base.py
telegram_framework/messages/media/image_default.py
telegram_framework/messages/reply/__init__.py
telegram_framework/messages/reply/reply.py
django_telegram_framework-5.0.1.dist-info/METADATA
django_telegram_framework-5.0.1.dist-info/WHEEL
django_telegram_framework-5.0.1.dist-info/top_level.txt
django_telegram_framework-5.0.1.dist-info/RECORD
