Metadata-Version: 2.4
Name: django-telegram-framework
Version: 5.0.1
Summary: Python Django package repository template
Home-page: https://github.com/quillcraftsman/django-telegram-framework
Author: quillcraftsman
Author-email: quill@craftsman.lol
License: Happy Code
Project-URL: Documentation, https://quillcraftsman.github.io/django-telegram-framework
Project-URL: Source, https://github.com/quillcraftsman/django-telegram-framework
Project-URL: Tracker, https://github.com/quillcraftsman/django-telegram-framework/issues
Project-URL: Release notes, https://github.com/quillcraftsman/django-telegram-framework/releases
Project-URL: Changelog, https://github.com/quillcraftsman/django-telegram-framework/releases
Project-URL: Download, https://pypi.org/project/django-telegram-framework/
Keywords: django,telegram,telegram-bot,framework,testing
Classifier: Development Status :: 3 - Alpha
Classifier: Intended Audience :: Developers
Classifier: License :: OSI Approved
Classifier: License :: Public Domain
Classifier: Programming Language :: Python :: 3
Classifier: Environment :: Web Environment
Classifier: Framework :: Django
Classifier: Operating System :: OS Independent
Classifier: Topic :: Software Development
Classifier: Topic :: Software Development :: Libraries
Classifier: Topic :: Software Development :: Libraries :: Python Modules
Classifier: Natural Language :: Russian
Requires-Python: >=3
License-File: LICENSE
Requires-Dist: Django>=5
Dynamic: author
Dynamic: author-email
Dynamic: classifier
Dynamic: description
Dynamic: description-content-type
Dynamic: home-page
Dynamic: keywords
Dynamic: license
Dynamic: license-file
Dynamic: project-url
Dynamic: requires-dist
Dynamic: requires-python
Dynamic: summary
